plover_delay/__init__.py
plover_delay-0.0.0.dist-info/LICENSE
plover_delay-0.0.0.dist-info/METADATA
plover_delay-0.0.0.dist-info/WHEEL
plover_delay-0.0.0.dist-info/entry_points.txt
plover_delay-0.0.0.dist-info/top_level.txt
plover_delay-0.0.0.dist-info/zip-safe
plover_delay-0.0.0.dist-info/RECORD
